jupyter_to_medium/__init__.py
jupyter_to_medium/_bundler.py
jupyter_to_medium/_command_line.py
jupyter_to_medium/_latex.py
jupyter_to_medium/_matplotlib_table.py
jupyter_to_medium/_postprocessors.py
jupyter_to_medium/_preprocesors.py
jupyter_to_medium/_publish_to_medium.py
jupyter_to_medium/_screenshot.py
jupyter_to_medium/static/fail.html
jupyter_to_medium/static/form.html
jupyter_to_medium/static/style.css
jupyter_to_medium/static/success.html
jupyter_to_medium/static/waiting.html
jupyter_to_medium-0.2.13.dist-info/LICENSE
jupyter_to_medium-0.2.13.dist-info/METADATA
jupyter_to_medium-0.2.13.dist-info/WHEEL
jupyter_to_medium-0.2.13.dist-info/entry_points.txt
jupyter_to_medium-0.2.13.dist-info/RECORD
