Metadata-Version: 2.1
Name: jupyter-to-medium
Version: 0.2.13
Summary: Publish a Jupyter Notebook as a Medium blogpost
Home-page: https://github.com/dexplo/jupyter_to_medium
License: MIT
Author: dexplo
Author-email: petrou.theodore@gmail.com
Maintainer: mjam03
Maintainer-email: markjamison03@gmail.com
Requires-Python: >=3.8,<3.11
Classifier: License :: OSI Approved :: MIT License
Classifier: Operating System :: OS Independent
Classifier: Programming Language :: Python :: 3
Classifier: Programming Language :: Python :: 3.8
Classifier: Programming Language :: Python :: 3.9
Classifier: Programming Language :: Python :: 3.10
Classifier: Programming Language :: Python :: 3.8
Classifier: Programming Language :: Python :: 3.9
Requires-Dist: beautifulsoup4 (>=4.12.0,<5.0.0)
Requires-Dist: jinja2 (==3.0.3)
Requires-Dist: jupyter (>=1.0.0,<2.0.0)
Requires-Dist: jupyter-contrib-nbextensions (>=0.7.0,<0.8.0)
Requires-Dist: matplotlib (>=3.7.1,<4.0.0)
Requires-Dist: nbconvert (>=7.2.10,<8.0.0)
Requires-Dist: numpy (>=1.24.2,<2.0.0)
Requires-Dist: requests (>=2.28.2,<3.0.0)
Project-URL: Changelog, https://github.com/dexplo/jupyter_to_medium/releases
Project-URL: Documentation, https://www.dexplo.org/jupyter_to_medium/
Project-URL: Repository, https://github.com/dexplo/jupyter_to_medium
